[
    {
        "title": "Tomo1",
        "image": "https://res.cloudinary.com/dlasojxtd/image/upload/v1714756378/mangas/Berserk%20-%20Tomo%2001/c0-1/Berserk_v0_000.webp"
    },
    {
        "title": "Tomo 2",
        "image": "https://res.cloudinary.com/dlasojxtd/image/upload/v1714763015/mangas/Berserk%20-%20Tomo%2002/c0-4/000.webp"
    },
    {
        "title": "Tomo 3",
        "image":
            "https://res.cloudinary.com/dlasojxtd/image/upload/v1714760499/mangas/Berserk%20-%20Tomo%2003/c0-6/Berserk_v0_000.webp"
    },
    {
        "title": "Tomo 4",
        "image":
            "https://res.cloudinary.com/dlasojxtd/image/upload/v1714763849/mangas/Berserk%20-%20Tomo%2004/c0-10/Berserk_v00_p000.webp"
    },
    {
        "title": "Tomo 5",
        "image":
            "https://res.cloudinary.com/dlasojxtd/image/upload/v1714754393/mangas/Berserk%20-%20Tomo%2005/c0-15/000.webp"
    }
]